sesamelib/__init__.py
sesamelib/ais_utils.py
sesamelib/constants.py
sesamelib/geometry.py
sesamelib/multitask.py
sesamelib/sesame_faust.py
sesamelib/utils.py
sesamelib-0.0.32.dist-info/LICENSE.txt
sesamelib-0.0.32.dist-info/METADATA
sesamelib-0.0.32.dist-info/WHEEL
sesamelib-0.0.32.dist-info/entry_points.txt
sesamelib-0.0.32.dist-info/top_level.txt
sesamelib-0.0.32.dist-info/RECORD
